<sect2>
<title>Installation of E2fsprogs</title>

<para>
Install E2fsprogs by running the following commands:
</para>

<para>
Please note that the empty --with-root-prefix= option below is supposed
to be like this. We did not forget to supply a value there.
</para>

<blockquote><literallayout>

	<userinput>./configure --prefix=/usr --with-root-prefix= \</userinput>
	<userinput>&nbsp;&nbsp;&nbsp;--enable-elf-shlibs &amp;&amp;</userinput>
	<userinput>make &amp;&amp;</userinput>
	<userinput>make install &amp;&amp;</userinput>
	<userinput>make install-libs</userinput>

</literallayout></blockquote>

</sect2>

