<?xml version="1.0" encoding="UTF-8"?>
<!DOCTYPE sect1 PUBLIC "-//OASIS//DTD DocBook XML V4.5//EN"
  "http://www.oasis-open.org/docbook/xml/4.5/docbookx.dtd" [
  <!ENTITY % general-entities SYSTEM "../general.ent">
  %general-entities;
]>

<sect1 id="ch-tools-patch" role="wrap">
  <?dbhtml filename="patch.html"?>

  <sect1info condition="script">
    <productname>patch</productname>
    <productnumber>&patch-version;</productnumber>
    <address>&patch-url;</address>
  </sect1info>

  <title>Patch-&patch-version;</title>

  <indexterm zone="ch-tools-patch">
    <primary sortas="a-Patch">Patch</primary>
    <secondary>инструменты</secondary>
  </indexterm>

  <sect2 role="package">
    <title/>

    <xi:include xmlns:xi="http://www.w3.org/2001/XInclude"
    href="../chapter08/patch.xml"
    xpointer="xpointer(/sect1/sect2[1]/para[1])"/>

    <segmentedlist>
      <segtitle>&buildtime;</segtitle>
      <segtitle>&diskspace;</segtitle>

      <seglistitem>
        <seg>&patch-tmp-sbu;</seg>
        <seg>&patch-tmp-du;</seg>
      </seglistitem>
    </segmentedlist>

  </sect2>

  <sect2 role="installation">
    <title>Установка Patch</title>

    <para>Подготовьте Patch для компиляции:</para>

<screen><userinput remap="configure">./configure --prefix=/usr   \
            --host=$LFS_TGT \
            --build=$(build-aux/config.guess)</userinput></screen>

    <para>Скомпилируйте пакет:</para>

<screen><userinput remap="make">make</userinput></screen>

    <para>Установите пакет:</para>

<screen><userinput remap="install">make DESTDIR=$LFS install</userinput></screen>

  </sect2>

  <sect2 role="content">
    <title/>

    <para>Подробная информация о пакете находится в
    <xref linkend="contents-patch" role="."/></para>

  </sect2>

</sect1>
