<sect1 id="ch-system-sed" xreflabel="Sed">
<title>Installing Sed-&sed-version;</title>
<?dbhtml filename="sed.html" dir="chapter06"?>

<para>The Sed package contains a stream editor.</para>

<screen>&buildtime; &sed-time;
&diskspace; &sed-compsize;</screen>

&aa-sed-down;
&aa-sed-dep;

<sect2><title>&nbsp;</title><para>&nbsp;</para></sect2>

<sect2>
<title>Installation of Sed</title>

<para>Prepare Sed for compilation:</para>

<screen><userinput>./configure --prefix=/usr --bindir=/bin</userinput></screen>

<para>Compile the package:</para>

<screen><userinput>make</userinput></screen>

<para>To have the results tested, issue:
<userinput>make check</userinput>.</para>

<para>And install the package:</para>

<screen><userinput>make install</userinput></screen>

</sect2>

&aa-sed-shortdesc;
&aa-sed-desc;

</sect1>

