<?xml version="1.0" encoding="UTF-8"?>
<!DOCTYPE sect1 PUBLIC "-//OASIS//DTD DocBook XML V4.5//EN"
  "http://www.oasis-open.org/docbook/xml/4.5/docbookx.dtd" [
  <!ENTITY % general-entities SYSTEM "../general.ent">
  %general-entities;
]>

<sect1 id="ch-config-introduction" revision="systemd">
  <?dbhtml filename="introduction.html"?>

  <title>Введение</title>

  <para>This chapter discusses configuration files and systemd services.
  First, the general configuration files needed to set up networking are
  presented.</para>

  <itemizedlist>
     <listitem>
       <para><xref linkend="ch-config-network" role="."/></para>
     </listitem>
     <listitem>
       <para><xref linkend="ch-config-hostname" role="."/></para>
     </listitem>
     <listitem>
       <para><xref linkend="ch-config-hosts" role="."/></para>
     </listitem>
  </itemizedlist>

  <para>Second, issues that affect the proper setup of devices are
  discussed.</para>

  <itemizedlist>
     <listitem>
       <para><xref linkend="ch-config-udev" role="."/></para>
     </listitem>
     <listitem>
       <para><xref linkend="ch-config-symlinks" role="."/></para>
     </listitem>
  </itemizedlist>

  <para>Third, configuring the system clock and keyboard layout is shown.</para>

  <itemizedlist>
     <listitem>
       <para><xref linkend="ch-config-clock" role="."/></para>
     </listitem>
     <listitem>
       <para><xref linkend="ch-config-console" role="."/></para>
     </listitem>
  </itemizedlist>

  <para>Fourth, a brief introduction to the scripts and configuration
  files used when the user logs into the system is presented.</para>

  <itemizedlist>
     <listitem>
       <para><xref linkend="ch-config-locale" role="."/></para>
     </listitem>
     <listitem>
       <para><xref linkend="ch-config-inputrc" role="."/></para>
     </listitem>
  </itemizedlist>

  <para>And finally, configuring the behavior of systemd is discussed.</para>

  <itemizedlist>
     <listitem>
       <para><xref linkend="ch-config-systemd-custom" role="."/></para>
     </listitem>
  </itemizedlist>

</sect1>
